prompt_versions_manager/__init__.py
prompt_versions_manager/prompt_versions_manager.py
prompt_versions_manager/examples/prompt_usage_examples.py
prompt_versions_manager-0.0.2.dist-info/METADATA
prompt_versions_manager-0.0.2.dist-info/WHEEL
prompt_versions_manager-0.0.2.dist-info/top_level.txt
prompt_versions_manager-0.0.2.dist-info/RECORD
