Metadata-Version: 2.2
Name: prompt-versions-manager
Version: 0.0.2
Summary: A delightful Python package for managing LLM prompts with versioning and i18n-style string management
Author-email: Pablo Schaffner <pablo@puntorigen.com>
License: MIT
Project-URL: Homepage, https://github.com/puntorigen/prompt-versions-manager
Keywords: llm,prompts,management,versioning,i18n
Classifier: Development Status :: 3 - Alpha
Classifier: Intended Audience :: Developers
Classifier: License :: OSI Approved :: MIT License
Classifier: Programming Language :: Python :: 3
Classifier: Programming Language :: Python :: 3.8
Classifier: Programming Language :: Python :: 3.9
Classifier: Programming Language :: Python :: 3.10
Classifier: Programming Language :: Python :: 3.11
Requires-Python: >=3.8
Requires-Dist: json5>=0.9.0
